kongxin/__init__.py
kongxin/api.py
kongxin/backend/__init__.py
kongxin/backend/base.py
kongxin/backend/filesystem_backend.py
kongxin/bank/__init__.py
kongxin/bank/_bank.py
kongxin/consumer.py
kongxin/core.py
kongxin/exception.py
kongxin/serialization.py
kongxin/types.py
kongxin-0.0.1.dist-info/LICENSE
kongxin-0.0.1.dist-info/METADATA
kongxin-0.0.1.dist-info/WHEEL
kongxin-0.0.1.dist-info/RECORD
